pprog/__init__.py
pprog/version.py
pprog/tests/__init__.py
pprog/tests/test_all.py
pprog-0.0.2.dist-info/METADATA
pprog-0.0.2.dist-info/WHEEL
pprog-0.0.2.dist-info/top_level.txt
pprog-0.0.2.dist-info/RECORD
