Metadata-Version: 2.1
Name: pprog
Version: 0.0.2
Summary: Python Programming Tools
Home-page: http://github.com/pprog-dev/
Author: Zhiqing Xiao
Author-email: xzq.xiaozhiqing@gmail.com
Classifier: Programming Language :: Python
